swagger_client/__init__.py
swagger_client/api_client.py
swagger_client/configuration.py
swagger_client/rest.py
swagger_client/api/__init__.py
swagger_client/api/custom_speech_datasets_for_model_adaptation_api.py
swagger_client/api/custom_speech_endpoints_api.py
swagger_client/api/custom_speech_model_evaluations_api.py
swagger_client/api/custom_speech_models_api.py
swagger_client/api/custom_speech_projects_api.py
swagger_client/api/custom_speech_transcriptions_api.py
swagger_client/api/custom_speech_web_hooks_api.py
swagger_client/api/service_health_api.py
swagger_client/models/__init__.py
swagger_client/models/base_model.py
swagger_client/models/base_model_deprecation_dates.py
swagger_client/models/base_model_features.py
swagger_client/models/base_model_links.py
swagger_client/models/base_model_properties.py
swagger_client/models/block_kind.py
swagger_client/models/commit_blocks_entry.py
swagger_client/models/component.py
swagger_client/models/custom_model.py
swagger_client/models/custom_model_deprecation_dates.py
swagger_client/models/custom_model_features.py
swagger_client/models/custom_model_links.py
swagger_client/models/custom_model_properties.py
swagger_client/models/dataset.py
swagger_client/models/dataset_kind.py
swagger_client/models/dataset_links.py
swagger_client/models/dataset_locales.py
swagger_client/models/dataset_properties.py
swagger_client/models/dataset_update.py
swagger_client/models/detailed_error_code.py
swagger_client/models/diarization_properties.py
swagger_client/models/diarization_speakers_properties.py
swagger_client/models/endpoint.py
swagger_client/models/endpoint_links.py
swagger_client/models/endpoint_properties.py
swagger_client/models/endpoint_properties_update.py
swagger_client/models/endpoint_update.py
swagger_client/models/entity_error.py
swagger_client/models/entity_reference.py
swagger_client/models/error.py
swagger_client/models/error_code.py
swagger_client/models/evaluation.py
swagger_client/models/evaluation_links.py
custom_swagger_client-1.0.0.dist-info/METADATA
custom_swagger_client-1.0.0.dist-info/WHEEL
custom_swagger_client-1.0.0.dist-info/top_level.txt
custom_swagger_client-1.0.0.dist-info/RECORD
