Metadata-Version: 2.1
Name: custom-swagger-client
Version: 1.0.0
Summary: Speech Services API v3.1
Home-page: 
Author-email: 
Keywords: Swagger,Speech Services API v3.1
Requires-Dist: certifi (>=2017.4.17)
Requires-Dist: python-dateutil (>=2.1)
Requires-Dist: six (>=1.10)
Requires-Dist: urllib3 (>=1.23)
